rune/__init__.py
rune/__main__.py
rune/adapters/__init__.py
rune/adapters/mcp/__init__.py
rune/adapters/persistence/__init__.py
rune/adapters/persistence/sessions.py
rune/adapters/ui/__init__.py
rune/adapters/ui/components.py
rune/adapters/ui/console.py
rune/adapters/ui/glyphs.py
rune/adapters/ui/live_display.py
rune/adapters/ui/render.py
rune/agent/__init__.py
rune/agent/factory.py
rune/agent/rich_wrappers.py
rune/cli/__init__.py
rune/cli/__main__.py
rune/cli/chat.py
rune/cli/models.py
rune/core/__init__.py
rune/core/context.py
rune/core/messages.py
rune/core/model_settings.py
rune/core/models.py
rune/core/tool_output.py
rune/core/tool_result.py
rune/core/prompts/__init__.py
rune/core/prompts/system_prompt.md
rune/tests/__init__.py
rune/tools/edit_file.py
rune/tools/fetch_url.py
rune/tools/get_metadata.py
rune/tools/grep.py
rune/tools/list_files.py
rune/tools/read_chunk.py
rune/tools/read_file.py
rune/tools/registry.py
rune/tools/run_command.py
rune/tools/run_python.py
rune/tools/todos.py
rune/tools/write_file.py
rune/utils/__init__.py
rune/utils/diff.py
rune/utils/stream.py
rune_code-0.16.0.dist-info/METADATA
rune_code-0.16.0.dist-info/WHEEL
rune_code-0.16.0.dist-info/entry_points.txt
rune_code-0.16.0.dist-info/top_level.txt
rune_code-0.16.0.dist-info/RECORD
