Metadata-Version: 2.4
Name: rune-code
Version: 0.16.0
Summary: A terminal first, opinionated AI coding agent written in Python. Works with almost any model via Pydantic-AI.
Author-email: Binal Patel <binalkp91@gmail.com>
License: Apache-2.0
Project-URL: Homepage, https://github.com/caesarnine/rune-code
Project-URL: Bug Tracker, https://github.com/caesarnine/rune-code/issues
Classifier: Programming Language :: Python :: 3
Classifier: Programming Language :: Python :: 3.10
Classifier: Programming Language :: Python :: 3.11
Classifier: Programming Language :: Python :: 3.12
Classifier: License :: OSI Approved :: Apache Software License
Classifier: Operating System :: OS Independent
Classifier: Environment :: Console
Classifier: Topic :: Software Development
Classifier: Topic :: Utilities
Classifier: Intended Audience :: Developers
Requires-Python: >=3.10
Requires-Dist: google-genai>=0.3.0
Requires-Dist: lxml>=5.3.2
Requires-Dist: pathspec>=0.12.1
Requires-Dist: pydantic>=2.0.0
Requires-Dist: python-dotenv>=1.0.1
Requires-Dist: prompt-toolkit>=3.0.0
Requires-Dist: rich>=13.9.4
Requires-Dist: pydantic-ai[examples]>=0.6.0
Requires-Dist: jupyter-client>=8.6.3
Requires-Dist: ipython>=8.37.0
Requires-Dist: ipykernel>=6.29.5
Requires-Dist: pydantic-xml>=2.17.2
Requires-Dist: html-to-markdown>=1.4.0
Requires-Dist: typer>=0.16.0
Requires-Dist: pytest-asyncio>=1.0.0
Requires-Dist: pytest-snapshot>=0.9.0
Provides-Extra: dev
Requires-Dist: ipykernel>=6.29.5; extra == "dev"
Requires-Dist: pre-commit>=3.7.1; extra == "dev"
Requires-Dist: pytest>=7.0.0; extra == "dev"
Requires-Dist: pytest-asyncio>=0.23.7; extra == "dev"
Requires-Dist: mypy>=1.0.0; extra == "dev"
Requires-Dist: ruff>=0.1.0; extra == "dev"
Requires-Dist: build>=1.2.1; extra == "dev"
Requires-Dist: twine>=5.0.0; extra == "dev"
Requires-Dist: pytest-snapshot>=0.9.0; extra == "dev"
Provides-Extra: vertex
Requires-Dist: google-cloud-aiplatform>=1.48.0; extra == "vertex"
